{
    "version": "5.0.2",
    "flags": {},
    "shapes": [
        {
            "label": "balloon",
            "points": [
                [
                    493.5,
                    257.5
                ],
                [
                    519.5,
                    259.5
                ],
                [
                    542.5,
                    268.5
                ],
                [
                    564.5,
                    278.5
                ],
                [
                    579.5,
                    294.5
                ],
                [
                    595.5,
                    311.5
                ],
                [
                    613.5,
                    347.5
                ],
                [
                    617.5,
                    372.5
                ],
                [
                    619.5,
                    402.5
                ],
                [
                    615.5,
                    427.5
                ],
                [
                    609.5,
                    453.5
                ],
                [
                    599.5,
                    476.5
                ],
                [
                    589.5,
                    497.5
                ],
                [
                    551.5,
                    541.5
                ],
                [
                    539.5,
                    555.5
                ],
                [
                    526.5,
                    561.5
                ],
                [
                    523.5,
                    568.5
                ],
                [
                    531.5,
                    577.5
                ],
                [
                    525.5,
                    579.5
                ],
                [
                    517.5,
                    581.5
                ],
                [
                    512.5,
                    579.5
                ],
                [
                    514.5,
                    573.5
                ],
                [
                    514.5,
                    568.5
                ],
                [
                    512.5,
                    563.5
                ],
                [
                    503.5,
                    561.5
                ],
                [
                    492.5,
                    557.5
                ],
                [
                    479.5,
                    549.5
                ],
                [
                    467.5,
                    541.5
                ],
                [
                    452.5,
                    530.5
                ],
                [
                    435.5,
                    515.5
                ],
                [
                    426.5,
                    505.5
                ],
                [
                    415.5,
                    495.5
                ],
                [
                    407.5,
                    480.5
                ],
                [
                    390.5,
                    456.5
                ],
                [
                    378.5,
                    419.5
                ],
                [
                    376.5,
                    395.5
                ],
                [
                    377.5,
                    369.5
                ],
                [
                    380.5,
                    346.5
                ],
                [
                    392.5,
                    320.5
                ],
                [
                    413.5,
                    290.5
                ],
                [
                    432.5,
                    278.5
                ],
                [
                    454.5,
                    264.5
                ],
                [
                    474.5,
                    259.5
                ],
                [
                    493.5,
                    257.5
                ]
            ],
            "shape_type": "polygon",
            "group_id": null,
            "flags": {}
        },
        {
            "label": "balloon",
            "points": [
                [
                    607.5,
                    532.5
                ],
                [
                    603.5,
                    566.5
                ],
                [
                    595.5,
                    589.5
                ],
                [
                    586.5,
                    610.5
                ],
                [
                    575.5,
                    624.5
                ],
                [
                    563.5,
                    639.5
                ],
                [
                    544.5,
                    647.5
                ],
                [
                    527.5,
                    656.5
                ],
                [
                    510.5,
                    658.5
                ],
                [
                    496.5,
                    661.5
                ],
                [
                    488.5,
                    660.5
                ],
                [
                    477.5,
                    655.5
                ],
                [
                    471.5,
                    654.5
                ],
                [
                    470.5,
                    649.5
                ],
                [
                    475.5,
                    643.5
                ],
                [
                    475.5,
                    637.5
                ],
                [
                    474.5,
                    626.5
                ],
                [
                    469.5,
                    603.5
                ],
                [
                    463.5,
                    583.5
                ],
                [
                    455.5,
                    559.5
                ],
                [
                    449.5,
                    542.5
                ],
                [
                    441.5,
                    529.5
                ],
                [
                    437.5,
                    520.5
                ],
                [
                    432.5,
                    513.5
                ],
                [
                    449.5,
                    527.5
                ],
                [
                    465.5,
                    541.5
                ],
                [
                    484.5,
                    554.5
                ],
                [
                    500.5,
                    560.5
                ],
                [
                    510.5,
                    563.5
                ],
                [
                    515.5,
                    569.5
                ],
                [
                    515.5,
                    576.5
                ],
                [
                    512.5,
                    580.5
                ],
                [
                    516.5,
                    583.5
                ],
                [
                    523.5,
                    583.5
                ],
                [
                    530.5,
                    577.5
                ],
                [
                    528.5,
                    572.5
                ],
                [
                    526.5,
                    567.5
                ],
                [
                    526.5,
                    563.5
                ],
                [
                    531.5,
                    561.5
                ],
                [
                    540.5,
                    553.5
                ],
                [
                    552.5,
                    541.5
                ],
                [
                    565.5,
                    522.5
                ],
                [
                    585.5,
                    502.5
                ],
                [
                    590.5,
                    492.5
                ],
                [
                    595.5,
                    483.5
                ],
                [
                    603.5,
                    499.5
                ],
                [
                    605.5,
                    517.5
                ],
                [
                    607.5,
                    529.5
                ],
                [
                    607.5,
                    532.5
                ]
            ],
            "shape_type": "polygon",
            "group_id": null,
            "flags": {}
        },
        {
            "label": "balloon",
            "points": [
                [
                    307.5,
                    435.5
                ],
                [
                    330.5,
                    440.5
                ],
                [
                    348.5,
                    444.5
                ],
                [
                    367.5,
                    451.5
                ],
                [
                    382.5,
                    459.5
                ],
                [
                    394.5,
                    468.5
                ],
                [
                    405.5,
                    479.5
                ],
                [
                    417.5,
                    493.5
                ],
                [
                    425.5,
                    505.5
                ],
                [
                    436.5,
                    520.5
                ],
                [
                    451.5,
                    547.5
                ],
                [
                    460.5,
                    576.5
                ],
                [
                    471.5,
                    611.5
                ],
                [
                    476.5,
                    632.5
                ],
                [
                    476.5,
                    641.5
                ],
                [
                    471.5,
                    648.5
                ],
                [
                    473.5,
                    655.5
                ],
                [
                    475.5,
                    660.5
                ],
                [
                    482.5,
                    667.5
                ],
                [
                    483.5,
                    671.5
                ],
                [
                    475.5,
                    675.5
                ],
                [
                    471.5,
                    676.5
                ],
                [
                    468.5,
                    672.5
                ],
                [
                    468.5,
                    669.5
                ],
                [
                    461.5,
                    663.5
                ],
                [
                    445.5,
                    668.5
                ],
                [
                    415.5,
                    677.5
                ],
                [
                    386.5,
                    682.5
                ],
                [
                    356.5,
                    686.5
                ],
                [
                    326.5,
                    685.5
                ],
                [
                    295.5,
                    681.5
                ],
                [
                    259.5,
                    668.5
                ],
                [
                    219.5,
                    638.5
                ],
                [
                    199.5,
                    611.5
                ],
                [
                    187.5,
                    581.5
                ],
                [
                    182.5,
                    551.5
                ],
                [
                    188.5,
                    515.5
                ],
                [
                    193.5,
                    497.5
                ],
                [
                    208.5,
                    479.5
                ],
                [
                    228.5,
                    458.5
                ],
                [
                    250.5,
                    445.5
                ],
                [
                    275.5,
                    437.5
                ],
                [
                    290.5,
                    437.5
                ],
                [
                    307.5,
                    435.5
                ]
            ],
            "shape_type": "polygon",
            "group_id": null,
            "flags": {}
        }
    ],
    "imagePath": "14666848163_8be8e37562_k.jpg",
    "imageData": null,
    "imageHeight": 2048,
    "imageWidth": 1357
}